tomfoolery/__init__.py
tomfoolery/_dump.py
tomfoolery/_load.py
tomfoolery/cli.py
tomfoolery/engine.py
tomfoolery/py.typed
tomfoolery/utilities.py
tomfoolery-1.1.1.dist-info/METADATA
tomfoolery-1.1.1.dist-info/WHEEL
tomfoolery-1.1.1.dist-info/entry_points.txt
tomfoolery-1.1.1.dist-info/licenses/LICENSE.txt
tomfoolery-1.1.1.dist-info/RECORD
