Metadata-Version: 2.1
Name: tomfoolery
Version: 1.1.1
Summary: CLI to generate Python dataclasses that model and load toml files (or other can-representated-as-a-dict files)
Project-URL: Homepage, https://github.com/matt-manes/tomfoolery
Project-URL: Documentation, https://github.com/matt-manes/tomfoolery/tree/main/docs
Project-URL: Source code, https://github.com/matt-manes/tomfoolery/tree/main/src/tomfoolery
Author-email: Matt Manes <mattmanes@pm.me>
License-File: LICENSE.txt
Keywords: dataclass,dataclasses,json,toml
Classifier: License :: OSI Approved :: MIT License
Classifier: Operating System :: OS Independent
Classifier: Programming Language :: Python :: 3
Requires-Python: >=3.10
Requires-Dist: ast-comments
Requires-Dist: black
Requires-Dist: dacite
Requires-Dist: isort
Requires-Dist: pathier
Requires-Dist: pytest
Requires-Dist: typing-extensions
